obra/README.md
obra/__init__.py
obra/_build_backend.py
obra/cli.py
obra/exceptions.py
obra/model_registry.py
obra/version_check.py
obra/.obra/BRIEFING_QUICK.md
obra/.obra/LLM_ONBOARDING.md
obra/.obra/templates/autonomous-progress-entry.yaml
obra/.obra/templates/checkpoint.yaml
obra/.obra/templates/continuation-prompt.md
obra/.obra/templates/escalation-report.md
obra/.obra/templates/handoff.md
obra/agents/__init__.py
obra/agents/base.py
obra/agents/claude_code.py
obra/agents/code_quality.py
obra/agents/deployer.py
obra/agents/docs.py
obra/agents/registry.py
obra/agents/security.py
obra/agents/test_execution.py
obra/agents/testing.py
obra/agents/tier_config.py
obra/agents/prompts/__init__.py
obra/agents/prompts/code_quality.txt
obra/agents/prompts/docs_analysis.txt
obra/agents/prompts/security_deep.txt
obra/agents/prompts/security_sweep.txt
obra/agents/prompts/testing_coverage.txt
obra/api/__init__.py
obra/api/client.py
obra/api/protocol.py
obra/api/schemas.py
obra/auth/__init__.py
obra/auth/oauth.py
obra/auth/tokens.py
obra/auth/types.py
obra/cli_commands/__init__.py
obra/cli_commands/upload_plan.py
obra/cli_commands/validate_plan.py
obra/config/__init__.py
obra/config/auth.py
obra/config/default_config.yaml
obra/config/llm.py
obra/config/loaders.py
obra/config/providers.py
obra/config/defaults/feedback.yaml
obra/config/defaults/feedback_classification.yaml
obra/config/explorer/__init__.py
obra/config/explorer/__main__.py
obra/config/explorer/app.py
obra/config/explorer/descriptions.py
obra/config/explorer/models.py
obra/config/explorer/utils.py
obra/config/explorer/styles/explorer.tcss
obra/config/explorer/widgets/__init__.py
obra/config/explorer/widgets/edit_modal.py
obra/config/explorer/widgets/help_overlay.py
obra/config/explorer/widgets/llm_wizard.py
obra/config/explorer/widgets/preset_picker.py
obra/config/explorer/widgets/quick_actions.py
obra/config/explorer/widgets/search_bar.py
obra/config/explorer/widgets/tree_view.py
obra-2.9.40.dist-info/METADATA
obra-2.9.40.dist-info/WHEEL
obra-2.9.40.dist-info/entry_points.txt
obra-2.9.40.dist-info/top_level.txt
obra-2.9.40.dist-info/RECORD
