Metadata-Version: 2.4
Name: obra
Version: 2.9.40
Summary: Obra - Cloud-native AI orchestration platform for autonomous software development
Author: Unpossible Creations, Inc.
License: Proprietary - All Rights Reserved
Project-URL: Homepage, https://obra.dev
Keywords: ai,orchestration,llm,automation,cloud,workflow,claude
Classifier: Development Status :: 4 - Beta
Classifier: Intended Audience :: Developers
Classifier: License :: Other/Proprietary License
Classifier: Programming Language :: Python :: 3
Classifier: Programming Language :: Python :: 3.12
Classifier: Programming Language :: Python :: 3.13
Classifier: Topic :: Software Development :: Libraries :: Python Modules
Classifier: Topic :: Scientific/Engineering :: Artificial Intelligence
Requires-Python: >=3.12
Requires-Dist: typer>=0.9.0
Requires-Dist: rich>=13.0.0
Requires-Dist: requests>=2.31.0
Requires-Dist: pyyaml>=6.0
Requires-Dist: pydantic>=2.0.0
Requires-Dist: watchdog>=3.0.0
Requires-Dist: python-dotenv>=1.0.0
Requires-Dist: textual>=0.47.0
Requires-Dist: tiktoken>=0.5.0
Requires-Dist: packaging>=21.0
Provides-Extra: test
Requires-Dist: pytest>=7.4.0; extra == "test"
Requires-Dist: pytest-cov>=4.1.0; extra == "test"
Requires-Dist: pytest-mock>=3.11.0; extra == "test"
Provides-Extra: dev
Requires-Dist: obra[test]; extra == "dev"
Requires-Dist: ruff>=0.1.0; extra == "dev"
Requires-Dist: mypy>=1.6.0; extra == "dev"
